babelgrid/__init__.py
babelgrid/babelgrid.py
babelgrid/quadtree.py
babelgrid/s2.py
babelgrid-0.1.7.dist-info/LICENSE.md
babelgrid-0.1.7.dist-info/METADATA
babelgrid-0.1.7.dist-info/WHEEL
babelgrid-0.1.7.dist-info/RECORD
