Metadata-Version: 2.1
Name: babelgrid
Version: 0.1.7
Summary: A common python API to work with different established grid systems.
Home-page: https://github.com/EL-BID/BabelGrid
License: AM-331-A3 Licencia de Software
Author: Joao Carabetta
Author-email: joao.carabetta@gmail.com
Requires-Python: >=3.9,<4.0
Classifier: License :: Other/Proprietary License
Classifier: Programming Language :: Python :: 3
Classifier: Programming Language :: Python :: 3.9
Classifier: Programming Language :: Python :: 3.10
Classifier: Programming Language :: Python :: 3.11
Classifier: Topic :: Software Development :: Build Tools
Classifier: Topic :: Software Development :: Libraries :: Python Modules
Requires-Dist: h3 (==3.6.3)
Requires-Dist: pygeotile
Requires-Dist: pyproj (==3.6.1)
Requires-Dist: s2sphere (==0.2.5)
Requires-Dist: shapely (>=2.0.1,<3.0.0)
Project-URL: Repository, https://github.com/EL-BID/BabelGrid
